ncbi_api/__init__.py
ncbi_api/compress.py
ncbi_api/geo.py
ncbi_api-1.0.dist-info/LICENSE
ncbi_api-1.0.dist-info/METADATA
ncbi_api-1.0.dist-info/WHEEL
ncbi_api-1.0.dist-info/top_level.txt
ncbi_api-1.0.dist-info/RECORD
