Metadata-Version: 2.1
Name: ncbi-api
Version: 1.0
Summary: NCBI数据下载及解析
Home-page: UNKNOWN
Author: zhangyafei
Author-email: zhangyafeii@foxmail.com
License: UNKNOWN
Platform: UNKNOWN
Classifier: Programming Language :: Python :: 3
Classifier: License :: OSI Approved :: MIT License
Classifier: Operating System :: OS Independent
Requires-Python: >=3.6
Requires-Dist: aiohttp
Requires-Dist: lxml
Requires-Dist: requests
Requires-Dist: zyf (>=0.6)
Requires-Dist: tqdm
Requires-Dist: pandas
